taskproc-0.25.3.dist-info/METADATA
taskproc-0.25.3.dist-info/WHEEL
taskproc-0.25.3.dist-info/entry_points.txt
taskproc/__init__.py
taskproc/__main__.py
taskproc/database.py
taskproc/executors.py
taskproc/future.py
taskproc/graph.py
taskproc/task.py
taskproc/types.py
taskproc-0.25.3.dist-info/RECORD
