Metadata-Version: 2.1
Name: taskproc
Version: 0.25.3
Summary: A lightweight task processing library written in pure Python
Home-page: https://github.com/koheimiya/taskproc
Author-Email: Kohei Miyaguchi <koheimiyaguchi@gmail.com>
License: MIT License
Project-URL: Homepage, https://github.com/koheimiya/taskproc
Project-URL: Repository, https://github.com/koheimiya/taskproc
Requires-Python: <4.0,>=3.10
Requires-Dist: typing-extensions<5.0.0,>=4.5.0
Requires-Dist: cloudpickle<3.0.0,>=2.2.1
Requires-Dist: networkx<4.0,>=3.1
Requires-Dist: click<9.0.0,>=8.1.3
Requires-Dist: tqdm<5.0.0,>=4.65.0
Requires-Dist: python-dotenv<2.0.0,>=1.0.0
Requires-Dist: exceptiongroup>=1.1.3
Requires-Dist: pudb>=2022.1.3; extra == "dev"
Requires-Dist: pytest>=7.4.2; extra == "dev"
Provides-Extra: dev
